demography/__init__.py
demography/data/uk/encodings.json
demography/data/uk/groups.json
demography/data/uk/map.json
demography/data/uk/regex
demography/data/uk/tree.json
demography-0.0.2.post3.dist-info/LICENSE
demography-0.0.2.post3.dist-info/METADATA
demography-0.0.2.post3.dist-info/WHEEL
demography-0.0.2.post3.dist-info/top_level.txt
demography-0.0.2.post3.dist-info/RECORD
